graphy_test_zhaohany/__init__.py
graphy_test_zhaohany/main.py
graphy_test_zhaohany/GAS_API/__init__.py
graphy_test_zhaohany/GAS_API/gas_api_test.py
graphy_test_zhaohany/GAS_API/gat_multi_head.py
graphy_test_zhaohany/GAS_API/gatconv.py
graphy_test_zhaohany/GAS_API/gcnconv.py
graphy_test_zhaohany/GAS_API/sparse.py
graphy_test_zhaohany/code_gen/__init__.py
graphy_test_zhaohany/code_gen/code_gen_test.py
graphy_test_zhaohany/code_gen/generate_gp_apis_code.py
graphy_test_zhaohany/code_gen/generate_header_code.py
graphy_test_zhaohany/code_gen/generate_pybind_code.py
graphy_test_zhaohany/code_gen/kernel.dsl
graphy_test_zhaohany/code_gen/main.py
graphy_test_zhaohany/kernel/CMakeLists.txt
graphy_test_zhaohany/kernel/bfs.cpp
graphy_test_zhaohany/kernel/csr.h
graphy_test_zhaohany/kernel/dlpack.h
graphy_test_zhaohany/kernel/generated_pybind.h
graphy_test_zhaohany/kernel/kernel.cpp
graphy_test_zhaohany/kernel/kernel.h
graphy_test_zhaohany/kernel/kernel_model.cpp
graphy_test_zhaohany/kernel/kernel_pybind.cpp
graphy_test_zhaohany/kernel/kernel_snb.cpp
graphy_test_zhaohany/kernel/kernel_snb.h
graphy_test_zhaohany/kernel/op.h
graphy_test_zhaohany/new_script/GAAN_citeseer_multi_head.py
graphy_test_zhaohany/new_script/GAAN_cora_multi_head.py
graphy_test_zhaohany/new_script/GAAN_pubmed_multi_head.py
graphy_test_zhaohany/new_script/GAAN_reddit_multi_head.py
graphy_test_zhaohany/new_script/GAT_graphpy.py
graphy_test_zhaohany/new_script/GAT_head_graphpy.py
graphy_test_zhaohany/new_script/GAT_multi_cora_snb.py
graphy_test_zhaohany/new_script/GAT_ogb_arx_multi_head.py
graphy_test_zhaohany/new_script/GAT_single_cora_snb.py
graphy_test_zhaohany/new_script/GAT_single_reddit_snb.py
graphy_test_zhaohany/new_script/GAT_v2_graphpy.py
graphy_test_zhaohany/new_script/GCN_citeseer_snb.py
graphy_test_zhaohany/new_script/GCN_citeseer_tf.py
graphy_test_zhaohany/new_script/GCN_cora_tf.py
graphy_test_zhaohany/new_script/GCN_graphpy.py
graphy_test_zhaohany/new_script/GCN_pubmed_snb.py
graphy_test_zhaohany-0.0.5.dist-info/METADATA
graphy_test_zhaohany-0.0.5.dist-info/WHEEL
graphy_test_zhaohany-0.0.5.dist-info/licenses/LICENSE
graphy_test_zhaohany-0.0.5.dist-info/RECORD
